barometer_logger.py
barometer/__init__.py
barometer/actions.py
barometer/background.py
barometer/data.py
barometer/graphs.py
barometer/paths.py
spectrum_barometer-2.2.2.dist-info/licenses/LICENSE.txt
web/__init__.py
web/app.py
web/routes.py
web/static/refresh.js
web/static/stabbypeng.png
web/templates/base.html
web/templates/dashboard.html
web/templates/stats.html
spectrum_barometer-2.2.2.dist-info/METADATA
spectrum_barometer-2.2.2.dist-info/WHEEL
spectrum_barometer-2.2.2.dist-info/entry_points.txt
spectrum_barometer-2.2.2.dist-info/top_level.txt
spectrum_barometer-2.2.2.dist-info/RECORD
