Metadata-Version: 2.4
Name: spectrum-barometer
Version: 2.2.2
Summary: Monitor barometric pressure from Spectrum SAX2V1S routers
Author-email: BobaTeagrl <Unsorted2750@proton.me>
License: MIT
Project-URL: Homepage, https://github.com/BobaTeagrl/spectrum-barometer
Project-URL: Repository, https://github.com/BobaTeagrl/spectrum-barometer
Project-URL: Issues, https://github.com/BobaTeagrl/spectrum-barometer/issues
Keywords: barometer,pressure,monitoring,spectrum,router,measurement,sax2v1s
Classifier: Development Status :: 5 - Production/Stable
Classifier: Intended Audience :: End Users/Desktop
Classifier: License :: OSI Approved
Classifier: Programming Language :: Python :: 3
Classifier: Programming Language :: Python :: 3.8
Classifier: Programming Language :: Python :: 3.9
Classifier: Programming Language :: Python :: 3.10
Classifier: Programming Language :: Python :: 3.11
Classifier: Programming Language :: Python :: 3.12
Requires-Python: >=3.8
License-File: LICENSE.txt
Requires-Dist: click>=8.0
Requires-Dist: pandas>=1.3
Requires-Dist: pyyaml>=5.4
Requires-Dist: requests>=2.26
Requires-Dist: urllib3>=1.26
Requires-Dist: matplotlib>=3.4
Requires-Dist: lxml>=4.6
Requires-Dist: html5lib>=1.1
Requires-Dist: numpy>=1.20
Requires-Dist: flask>=2.0
Requires-Dist: qbstyles
Requires-Dist: psutil>=5.8
Dynamic: license-file
